mlops/__init__.py
mlops/config.py
mlops/dataset_generate.py
milena_efimenko_17-0.0.1.dist-info/METADATA
milena_efimenko_17-0.0.1.dist-info/WHEEL
milena_efimenko_17-0.0.1.dist-info/top_level.txt
milena_efimenko_17-0.0.1.dist-info/RECORD
