Metadata-Version: 2.1
Name: milena-efimenko-17
Version: 0.0.1
Summary: A short description of the project.
Author: milena_efimenko
Classifier: Programming Language :: Python :: 3
Requires-Python: >=3.8
